{"orientation": [0.1927369087934494, -0.02587476558983326, -0.014696395955979824, 0.9807991981506348], "scale": [1.0, 1.0, 1.0], "complaints": [{"object": "half_auricularia-putkli", "message": "APPEARANCE: Confirm object visual appearance.\nRequirements:\n- make sure the object has a valid texture or appearance (e.g., texture not black,\n       transparency rendered correctly, etc).\n- make sure any glass parts are transparent (would this object contain glass? e.g.\n       wall pictures, clocks, etc. - anything wrong)\n- compare the object against the 3ds Max image that should open up now.", "complaint": "texture black", "processed": false, "new": true}]}