{"orientation": [0.0, -4.3655745685100555e-10, 1.0000001192092896, 0.0], "scale": [1.0, 1.0, 1.0], "complaints": [{"object": "walker-fdklhj", "message": "Confirm reasonable bounding box size:\n24.74m, 7.95m, 11.97m\nMake sure these sizes are within the same order of magnitude you expect from this object IRL.\nIf the scale is off, please let us know by a factor of how much (for example, 1000 if something\nthat's supposed to be 1mm is 1m instead) in your complaint note.", "complaint": "x100", "processed": true}]}